{
  "catNum": "SEM028C",
  "author": "Sangharakshita",
  "title": "Contents of Women-s Order Convention 1987 - General Questions and Answers",
  "status": "published",
  "content": "<b>GENERAL QUESTIONS AND ANSWERS</b></p>\n<p><b>Contents</b><br/>\n<b>137</b>Etiquette when visiting Buddhist sites <br/>\n<b>138</b>Recitation of confessional verses<br/>\n<b>139</b>The Jataka stories - the &quot;Old Testament of Buddhism&quot;!?<br/>\nEnjoying the spiritual life<br/>\n<b>140</b>Viewing past, present and future from outside time<br/>\nBhante's early precognitive experiences<br/>\nThe subjectivity of time and the advantages of reflecting on this at the time of<br/>\nsomeone's death<br/>\n<b>142</b>The historical significance of women only ordaining women in the Western<br/>\nBuddhist Order.<br/>\n<b>143</b>Different Sanghas in the Buddhist world<br/>\n<b>145</b>All women being subject to men in the Theravada tradition<br/>\nPadmasambhava mantra chanting and the popularity of Padmasambhava in the<br/>\n(F)WBO<br/>\n<b>146</b>Bhante's link with Padmasambhava<br/>\nThe connection between the West/Western and death and spiritual rebirth<br/>\nAmitabha and Padmasambhava<br/>\n<b>147</b>The Bodhiangas and the Spiral Path<br/>\nThe unification of the three yanas in the anagarika/anagarik  and/or<br/>\nDharmachari/Dharmacharini way<br/>\n<b>149</b>Samayasattva and Jnanasattva<br/>\n<b>150</b>The wild goose in India<br/>\n<b>151</b>Right Livelihood and its four main objectives<br/>\n<b>153</b>Collecting information about centres via surveys/questionnairres<br/>\n<b>154</b>The anagarika ceremony<br/>\nBhante's photographs on shrines?<br/>\n<b>155</b>Consecration of rupas etc.<br/>\n<b>156</b>Form and content in art<br/>\n<b>158</b>The Order and other spiritual traditions<br/>\n<b>159</b>'Accidentally' Going for Refuge to another teacher/tradition<br/>\n<b>160</b>The importance of attending Order Conventions<br/>\nProgress and maturity in the Women's wing of the Order<br/>\n<b>161</b>Concern over 'negative competitiveness' in the men's wing of the Order<br/>\n<b>162</b>Bhante's reflections on the 1987 Order Conventions<br/>\n<b>164</b>The phases of expression of Bhante's teachings<br/>\nThe natural death of the question and answer session<br/>\n<b>165</b>Bhante's literary ideas<br/>\n\n",
  "path": "seminartexts/SEM028C_Contents_of_Women-s_Order_Convention_1987_-_General_Questions_and_Answers.pdf",
  "soft_deleted": false,
  "isTranscript": false,
  "pages": 1,
  "page": "<b>GENERAL QUESTIONS AND ANSWERS</b></p>\n<p><b>Contents</b><br/>\n<b>137</b>Etiquette when visiting Buddhist sites <br/>\n<b>138</b>Recitation of confessional verses<br/>\n<b>139</b>The Jataka stories - the &quot;Old Testament of Buddhism&quot;!?<br/>\nEnjoying the spiritual life<br/>\n<b>140</b>Viewing past, present and future from outside time<br/>\nBhante's early precognitive experiences<br/>\nThe subjectivity of time and the advantages of reflecting on this at the time of<br/>\nsomeone's death<br/>\n<b>142</b>The historical significance of women only ordaining women in the Western<br/>\nBuddhist Order.<br/>\n<b>143</b>Different Sanghas in the Buddhist world<br/>\n<b>145</b>All women being subject to men in the Theravada tradition<br/>\nPadmasambhava mantra chanting and the popularity of Padmasambhava in the<br/>\n(F)WBO<br/>\n<b>146</b>Bhante's link with Padmasambhava<br/>\nThe connection between the West/Western and death and spiritual rebirth<br/>\nAmitabha and Padmasambhava<br/>\n<b>147</b>The Bodhiangas and the Spiral Path<br/>\nThe unification of the three yanas in the anagarika/anagarik  and/or<br/>\nDharmachari/Dharmacharini way<br/>\n<b>149</b>Samayasattva and Jnanasattva<br/>\n<b>150</b>The wild goose in India<br/>\n<b>151</b>Right Livelihood and its four main objectives<br/>\n<b>153</b>Collecting information about centres via surveys/questionnairres<br/>\n<b>154</b>The anagarika ceremony<br/>\nBhante's photographs on shrines?<br/>\n<b>155</b>Consecration of rupas etc.<br/>\n<b>156</b>Form and content in art<br/>\n<b>158</b>The Order and other spiritual traditions<br/>\n<b>159</b>'Accidentally' Going for Refuge to another teacher/tradition<br/>\n<b>160</b>The importance of attending Order Conventions<br/>\nProgress and maturity in the Women's wing of the Order<br/>\n<b>161</b>Concern over 'negative competitiveness' in the men's wing of the Order<br/>\n<b>162</b>Bhante's reflections on the 1987 Order Conventions<br/>\n<b>164</b>The phases of expression of Bhante's teachings<br/>\nThe natural death of the question and answer session<br/>\n<b>165</b>Bhante's literary ideas<br/>\n\n"
}