{
  "catNum": "SEM044C",
  "author": "Sangharakshita",
  "title": "Contents of Fifteen Points for Buddhist Parents - Questions and Answers",
  "status": "published",
  "content": "<p style=\"text-align: center\"><strong>Questions and Answers on Fifteen Points for Buddhist Parents <br>23rd April 1994 at the London Buddhist Arts Centre<br>Contents</strong></p><p><br>1 What to tell children of Buddhist parents about celebrations such as Christmas <br>2 A special puja for children? When can children start learning meditation? <br>Difficulties with Christian religious education in schools <br>3 Looking after one's friend's children in the Mov ement <br>4 Is a father/male important for a developing boy? <br>5 Doubts about paternity TV and computer games <br>6 'Materialism' <br>7 Single parents living together in communities? Can parents attain stream entry? <br>8 Teaching children to meditate 'Coming of age' ceremonies? <br>9 Trying to preserve a relationship 'for the sake of the children' <br>10 Can parenthood be a path that leads to insight? <br>An Anagarika and a Brahmachari <br>11 Extended families Do fathers and mothers play different roles in brin ging up children? <br>13 Feeling marginalised as a parent in the FWBO <br>14 Should children be regarded as little adults? <br>15 Equal parental responsibility? If so, from when ? <br>16 Doing things wholeheartedly <br>17 Are parents over-protective of their children? <br>18 Breaking a law because one thinks it is unjust? <br>19 Buddhist schools? Unplanned pregnancies</p>",
  "path": "seminartexts/SEM044C_Contents_of_Fifteen_Points_for_Buddhist_Parents_-_Questions_and_Answers.pdf",
  "soft_deleted": false,
  "isTranscript": false,
  "pages": 1,
  "page": "<p style=\"text-align: center\"><strong>Questions and Answers on Fifteen Points for Buddhist Parents <br>23rd April 1994 at the London Buddhist Arts Centre<br>Contents</strong></p><p><br>1 What to tell children of Buddhist parents about celebrations such as Christmas <br>2 A special puja for children? When can children start learning meditation? <br>Difficulties with Christian religious education in schools <br>3 Looking after one's friend's children in the Mov ement <br>4 Is a father/male important for a developing boy? <br>5 Doubts about paternity TV and computer games <br>6 'Materialism' <br>7 Single parents living together in communities? Can parents attain stream entry? <br>8 Teaching children to meditate 'Coming of age' ceremonies? <br>9 Trying to preserve a relationship 'for the sake of the children' <br>10 Can parenthood be a path that leads to insight? <br>An Anagarika and a Brahmachari <br>11 Extended families Do fathers and mothers play different roles in brin ging up children? <br>13 Feeling marginalised as a parent in the FWBO <br>14 Should children be regarded as little adults? <br>15 Equal parental responsibility? If so, from when ? <br>16 Doing things wholeheartedly <br>17 Are parents over-protective of their children? <br>18 Breaking a law because one thinks it is unjust? <br>19 Buddhist schools? Unplanned pregnancies</p>"
}