{
  "catNum": "SEM045C",
  "author": "Sangharakshita",
  "title": "Contents of Twenty Years in the UK - Interview",
  "status": "published",
  "content": "<p style=\"text-align: center\"><strong>Interview with Nagabodhi <br>20th Year in the U.K. <br>Contents </strong></p><p><br><br>1 Bhante's experience of Buddhism in the West on h is return from India <br>4 A New Buddhist Movement <br>5 Bhante's eventual disillusionment with the New I ndia after independence <br>Other possible reasons for leaving India <br>7 Bhante, the reluctant revolutionary <br>8 Bhante's liking of Holman Hunt's pre-Raphaelite painting 'The Scapegoat' <br>9 Did the FWBO recruit mainly among hippies in the sixties? <br>12 Has the FWBO gone the way that Bhante hoped? <br>14 The importance of clarity <br>16 Bhante's priorities for the future <br>18 Quantum leaps in the history of the FWBO/WBO</p>",
  "path": "seminartexts/SEM045C_Contents_of_Twenty_Years_in_the_UK_-_Interview.pdf",
  "soft_deleted": false,
  "isTranscript": false,
  "pages": 1,
  "page": "<p style=\"text-align: center\"><strong>Interview with Nagabodhi <br>20th Year in the U.K. <br>Contents </strong></p><p><br><br>1 Bhante's experience of Buddhism in the West on h is return from India <br>4 A New Buddhist Movement <br>5 Bhante's eventual disillusionment with the New I ndia after independence <br>Other possible reasons for leaving India <br>7 Bhante, the reluctant revolutionary <br>8 Bhante's liking of Holman Hunt's pre-Raphaelite painting 'The Scapegoat' <br>9 Did the FWBO recruit mainly among hippies in the sixties? <br>12 Has the FWBO gone the way that Bhante hoped? <br>14 The importance of clarity <br>16 Bhante's priorities for the future <br>18 Quantum leaps in the history of the FWBO/WBO</p>"
}